[
    {
        "spice: small cardamom": {
            "auctioneer": "the kerala cardamom processing and marketing company limited",
            "avg. price (rs./kg)": "2805.71",
            "date of auction": "10-jul-2026",
            "max price (rs./kg)": "3698.00",
            "no.of lots": "199",
            "qty arrived (kgs)": "52208.1",
            "qty sold (kgs)": "47264.2"
        }
    },
    {
        "spice: large cardamom": {
            "date": "09-jul-2026",
            "market": "singtam",
            "price (rs./kg)": "1350.00",
            "type": "badadana"
        }
    },
    {
        "spice: large cardamom": {
            "date": "09-jul-2026",
            "market": "singtam",
            "price (rs./kg)": "1250.00",
            "type": "chotadana"
        }
    },
    {
        "spice: large cardamom": {
            "date": "09-jul-2026",
            "market": "gangtok",
            "price (rs./kg)": "1500.00",
            "type": "badadana"
        }
    },
    {
        "spice: large cardamom": {
            "date": "09-jul-2026",
            "market": "gangtok",
            "price (rs./kg)": "1350.00",
            "type": "chotadana"
        }
    },
    {
        "spice: large cardamom": {
            "date": "09-jul-2026",
            "market": "siliguri",
            "price (rs./kg)": "1867.00",
            "type": "badadana"
        }
    },
    {
        "spice: large cardamom": {
            "date": "09-jul-2026",
            "market": "siliguri",
            "price (rs./kg)": "1613.00",
            "type": "chotadana"
        }
    }
]