[
    {
        "spice: small cardamom": {
            "auctioneer": "south indian green cardamom company ltd",
            "avg. price (rs./kg)": "2414.66",
            "date of auction": "24-dec-2025",
            "max price (rs./kg)": "2805.00",
            "no.of lots": "305",
            "qty arrived (kgs)": "96539.3",
            "qty sold (kgs)": "76933.9"
        }
    },
    {
        "spice: small cardamom": {
            "auctioneer": "cardamom growersforever private limited",
            "avg. price (rs./kg)": "2399.81",
            "date of auction": "24-dec-2025",
            "max price (rs./kg)": "2856.00",
            "no.of lots": "195",
            "qty arrived (kgs)": "31383.6",
            "qty sold (kgs)": "30501.6"
        }
    },
    {
        "spice: large cardamom": {
            "date": "18-dec-2025",
            "market": "singtam",
            "price (rs./kg)": "1700.00",
            "type": "badadana"
        }
    },
    {
        "spice: large cardamom": {
            "date": "18-dec-2025",
            "market": "singtam",
            "price (rs./kg)": "1500.00",
            "type": "chotadana"
        }
    },
    {
        "spice: large cardamom": {
            "date": "18-dec-2025",
            "market": "gangtok",
            "price (rs./kg)": "1625.00",
            "type": "badadana"
        }
    },
    {
        "spice: large cardamom": {
            "date": "18-dec-2025",
            "market": "gangtok",
            "price (rs./kg)": "1475.00",
            "type": "chotadana"
        }
    },
    {
        "spice: large cardamom": {
            "date": "18-dec-2025",
            "market": "siliguri",
            "price (rs./kg)": "1800.00",
            "type": "badadana"
        }
    },
    {
        "spice: large cardamom": {
            "date": "18-dec-2025",
            "market": "siliguri",
            "price (rs./kg)": "1595.00",
            "type": "chotadana"
        }
    }
]